voice_transcriber/__init__.py
voice_transcriber/config.py
voice_transcriber/voice_transcriber.py
voice_transcriber_client-1.0.0.data/scripts/voice-transcriber
voice_transcriber_client-1.0.0.dist-info/METADATA
voice_transcriber_client-1.0.0.dist-info/WHEEL
voice_transcriber_client-1.0.0.dist-info/top_level.txt
voice_transcriber_client-1.0.0.dist-info/RECORD
