Metadata-Version: 2.1
Name: voice-transcriber-client
Version: 1.0.0
Summary: A python client for the https://github.com/jamesridgway/voice-transcriber project.
Home-page: https://github.com/jamesridgway/voice-transcriber-client
Author: James Ridgway
Author-email: james@jamesridgway.co.uk
License: MIT
Platform: UNKNOWN
Requires-Dist: pyperclip
Requires-Dist: requests
